netbox_ssl/__init__.py
netbox_ssl/checks.py
netbox_ssl/dashboard.py
netbox_ssl/navigation.py
netbox_ssl/template_content.py
netbox_ssl/urls.py
netbox_ssl/api/__init__.py
netbox_ssl/api/urls.py
netbox_ssl/api/views.py
netbox_ssl/api/serializers/__init__.py
netbox_ssl/api/serializers/assignments.py
netbox_ssl/api/serializers/certificates.py
netbox_ssl/filtersets/__init__.py
netbox_ssl/filtersets/assignments.py
netbox_ssl/filtersets/certificates.py
netbox_ssl/forms/__init__.py
netbox_ssl/forms/assignments.py
netbox_ssl/forms/certificates.py
netbox_ssl/graphql/__init__.py
netbox_ssl/graphql/schema.py
netbox_ssl/graphql/types.py
netbox_ssl/migrations/0001_initial.py
netbox_ssl/migrations/__init__.py
netbox_ssl/models/__init__.py
netbox_ssl/models/assignments.py
netbox_ssl/models/certificates.py
netbox_ssl/tables/__init__.py
netbox_ssl/tables/assignments.py
netbox_ssl/tables/certificates.py
netbox_ssl/templatetags/__init__.py
netbox_ssl/utils/__init__.py
netbox_ssl/utils/parser.py
netbox_ssl/views/__init__.py
netbox_ssl/views/assignments.py
netbox_ssl/views/certificates.py
netbox_ssl-0.1.0.dist-info/licenses/LICENSE
netbox_ssl-0.1.0.dist-info/METADATA
netbox_ssl-0.1.0.dist-info/WHEEL
netbox_ssl-0.1.0.dist-info/top_level.txt
netbox_ssl-0.1.0.dist-info/RECORD
