Metadata-Version: 2.4
Name: netbox-ssl
Version: 0.1.0
Summary: NetBox plugin for TLS/SSL certificate management - Project Janus
Author: NetBox SSL Team
License: Apache-2.0
Project-URL: Homepage, https://github.com/ctrl-alt-automate/netbox-ssl
Project-URL: Documentation, https://github.com/ctrl-alt-automate/netbox-ssl/wiki
Project-URL: Repository, https://github.com/ctrl-alt-automate/netbox-ssl
Keywords: netbox,plugin,ssl,tls,certificate,pki
Classifier: Development Status :: 3 - Alpha
Classifier: Framework :: Django
Classifier: Intended Audience :: System Administrators
Classifier: License :: OSI Approved :: Apache Software License
Classifier: Programming Language :: Python :: 3
Classifier: Programming Language :: Python :: 3.10
Classifier: Programming Language :: Python :: 3.11
Classifier: Programming Language :: Python :: 3.12
Requires-Python: >=3.10
License-File: LICENSE
Requires-Dist: cryptography>=41.0.0
Dynamic: license-file
